{
	"schemaVersion": 1,
	"id": "share-projects-downloader",
	"version": "${version}",
	"name": "Share-Projects Downloader",
	"description": "Downloader & file manager for Share-Projects schematics.",
	"authors": [
		"Andrews54757"
	],
	"contact": {
		"homepage": "https://github.com/Storage-Tech-2/ST2-Downloader",
		"sources": "https://github.com/Storage-Tech-2/ST2-Downloader",
		"issues": "https://github.com/Storage-Tech-2/ST2-Downloader/issues"
	},
	"license": "MIT",
	"icon": "assets/st2-downloader/icon.png",
	"environment": "client",
	"entrypoints": {
		"main": [
			"com.andrews.spdownloader.SPDownloader"
		],
		"client": [
			"com.andrews.spdownloader.SPDownloaderClient"
		]
	},
	"depends": {
        "minecraft": "1.21.4",
		"java": ">=21",
		"fabric-api": "*"
	},
	"mixins": [
		"share-projects-downloader.mixins.json",
		"share-projects-downloader.client.mixins.json"
	],
	"suggests": {
		"another-mod": "*"
	}
}
